azure/mgmt/edgezones/__init__.py
azure/mgmt/edgezones/_client.py
azure/mgmt/edgezones/_configuration.py
azure/mgmt/edgezones/_model_base.py
azure/mgmt/edgezones/_patch.py
azure/mgmt/edgezones/_serialization.py
azure/mgmt/edgezones/_version.py
azure/mgmt/edgezones/py.typed
azure/mgmt/edgezones/aio/__init__.py
azure/mgmt/edgezones/aio/_client.py
azure/mgmt/edgezones/aio/_configuration.py
azure/mgmt/edgezones/aio/_patch.py
azure/mgmt/edgezones/aio/operations/__init__.py
azure/mgmt/edgezones/aio/operations/_operations.py
azure/mgmt/edgezones/aio/operations/_patch.py
azure/mgmt/edgezones/models/__init__.py
azure/mgmt/edgezones/models/_enums.py
azure/mgmt/edgezones/models/_models.py
azure/mgmt/edgezones/models/_patch.py
azure/mgmt/edgezones/operations/__init__.py
azure/mgmt/edgezones/operations/_operations.py
azure/mgmt/edgezones/operations/_patch.py
azure_mgmt_edgezones-1.0.0b2.dist-info/LICENSE
azure_mgmt_edgezones-1.0.0b2.dist-info/METADATA
azure_mgmt_edgezones-1.0.0b2.dist-info/WHEEL
azure_mgmt_edgezones-1.0.0b2.dist-info/top_level.txt
azure_mgmt_edgezones-1.0.0b2.dist-info/RECORD
